beatprofiler/__init__.py
beatprofiler-1.0.0.dist-info/METADATA
beatprofiler-1.0.0.dist-info/WHEEL
beatprofiler-1.0.0.dist-info/licenses/LICENSE
beatprofiler-1.0.0.dist-info/RECORD
