Metadata-Version: 2.3
Name: beatprofiler
Version: 1.0.0
Summary: Cardiac functional analysis tool for in vitro models
Project-URL: Homepage, https://beatprofiler.github.io
Project-URL: GitHub, https://github.com/youngbinkim0/BeatProfiler
Author-email: Youngbin Kim <xmicroby@gmail.com>, Kunlun Wang <kw2964@columbia.edu>
License-File: LICENSE
Keywords: analysis,beatprofiler,calcium,cardiac,cardiomyocytes,contractility,eht,force,function,iPSC,monolayer,spheroid,tissue,tissue engineering
Classifier: License :: OSI Approved :: GNU General Public License v3 (GPLv3)
Classifier: Operating System :: OS Independent
Classifier: Programming Language :: Python :: 3
Requires-Python: >=3.8
Requires-Dist: nd2reader
Requires-Dist: openpyxl
Requires-Dist: pyts
Requires-Dist: scikit-video
Requires-Dist: tifffile
Provides-Extra: tissue
Requires-Dist: ultralytics; extra == 'tissue'
